spkg/__about__.py
spkg/__init__.py
spkg/__main__.py
spkg/action/__init__.py
spkg/ci/__init__.py
spkg/cli/__init__.py
spkg/hatch/__init__.py
spkg/log/__init__.py
spkg-1.1.5.dist-info/METADATA
spkg-1.1.5.dist-info/WHEEL
spkg-1.1.5.dist-info/entry_points.txt
spkg-1.1.5.dist-info/licenses/LICENSE
spkg-1.1.5.dist-info/RECORD
