Metadata-Version: 2.1
Name: spkg
Version: 1.1.5
Summary: SPKG (Simple Packager) - A command line tools for building and uploading python packages.
Project-URL: Documentation, https://github.com/xuanzhi33/spkg#readme
Project-URL: Issues, https://github.com/xuanzhi33/spkg/issues
Project-URL: Source, https://github.com/xuanzhi33/spkg
Author-email: xuanzhi33 <xuanzhi33@qq.com>
License-Expression: GPL-3.0-only
License-File: LICENSE
Classifier: Development Status :: 4 - Beta
Classifier: Programming Language :: Python
Classifier: Programming Language :: Python :: 3.8
Classifier: Programming Language :: Python :: 3.9
Classifier: Programming Language :: Python :: 3.10
Classifier: Programming Language :: Python :: 3.11
Classifier: Programming Language :: Python :: 3.12
Classifier: Programming Language :: Python :: Implementation :: CPython
Classifier: Programming Language :: Python :: Implementation :: PyPy
Requires-Python: >=3.8
Requires-Dist: click
Requires-Dist: hatch
